mcp_image_cutout/__init__.py
mcp_image_cutout/server.py
mcp_image_cutout-0.2.8.dist-info/METADATA
mcp_image_cutout-0.2.8.dist-info/WHEEL
mcp_image_cutout-0.2.8.dist-info/entry_points.txt
mcp_image_cutout-0.2.8.dist-info/licenses/LICENSE
mcp_image_cutout-0.2.8.dist-info/RECORD
