Metadata-Version: 2.4
Name: mcp-image-cutout
Version: 0.2.8
Summary: MCP服务器：图像编辑工具，提供显著性分割、背景移除等图像处理功能
Project-URL: Homepage, https://github.com/fengjinchao/mcp-image-cutout
Project-URL: Repository, https://github.com/fengjinchao/mcp-image-cutout
Project-URL: Documentation, https://github.com/fengjinchao/mcp-image-cutout#readme
Project-URL: Issues, https://github.com/fengjinchao/mcp-image-cutout/issues
Author-email: fengjinchao <fengjinchao@example.com>
License: MIT
License-File: LICENSE
Keywords: ai,computer-vision,cutout,image,mcp,volcengine
Classifier: Development Status :: 4 - Beta
Classifier: Intended Audience :: Developers
Classifier: License :: OSI Approved :: MIT License
Classifier: Programming Language :: Python :: 3
Classifier: Programming Language :: Python :: 3.10
Classifier: Programming Language :: Python :: 3.11
Classifier: Programming Language :: Python :: 3.12
Classifier: Topic :: Scientific/Engineering :: Artificial Intelligence
Classifier: Topic :: Scientific/Engineering :: Image Processing
Classifier: Topic :: Software Development :: Libraries :: Python Modules
Requires-Python: >=3.10
Requires-Dist: httpx[socks]>=0.28.1
Requires-Dist: mcp[cli]>=1.12.0
Requires-Dist: pillow>=9.0.0
Requires-Dist: volcengine>=1.0.0
